saxton2006/__init__.py
saxton2006/info.py
saxton2006/table1.py
saxton2006/version.py
saxton2006/clean/readme.rst
saxton2006/clean/table3.csv
saxton2006-1.1.0.dist-info/AUTHORS.rst
saxton2006-1.1.0.dist-info/LICENSE
saxton2006-1.1.0.dist-info/METADATA
saxton2006-1.1.0.dist-info/WHEEL
saxton2006-1.1.0.dist-info/top_level.txt
saxton2006-1.1.0.dist-info/RECORD
