Metadata-Version: 2.1
Name: saxton2006
Version: 1.1.0
Summary: Formalisms published in Saxton and Rawls (2006)
Author-email: revesansparole <revesansparole@gmail.com>
Maintainer-email: revesansparole <revesansparole@gmail.com>, Jerome Chopard <revesansparole@gmail.com>, jchopard <jerome.chopard@itk.fr>
License: cc_by_nc
Project-URL: repository, https://gitlab.com/b326/saxton2006
Project-URL: pip, https://pypi.org/project/saxton2006/1.1.0/
Project-URL: conda, https://anaconda.org/revesansparole/saxton2006
Project-URL: doc, https://b326.gitlab.io/saxton2006/
Project-URL: pypi, https://badge.fury.io/py/saxton2006
Classifier: Development Status :: 2 - Pre-Alpha
Classifier: Intended Audience :: Developers
Classifier: License :: OSI Approved :: BSD License
Classifier: Natural Language :: English
Classifier: Programming Language :: Python
Classifier: Programming Language :: Python :: 3
Classifier: Programming Language :: Python :: 3 :: Only
Classifier: Programming Language :: Python :: 3.11
Classifier: Programming Language :: Python :: 3.8
Requires-Python: >=3.8
License-File: LICENSE
License-File: AUTHORS.rst
Provides-Extra: doc
Requires-Dist: sphinx ; extra == 'doc'
Requires-Dist: sphinx-gallery ; extra == 'doc'
Requires-Dist: sphinx-rtd-theme ; extra == 'doc'
Provides-Extra: dvlpt
Requires-Dist: twine ; extra == 'dvlpt'
Provides-Extra: example
Requires-Dist: matplotlib ; extra == 'example'
Requires-Dist: numpy ; extra == 'example'
Provides-Extra: script
Requires-Dist: pandas ; extra == 'script'
Provides-Extra: test
Requires-Dist: coverage ; extra == 'test'
Requires-Dist: pandas ; extra == 'test'
Requires-Dist: pytest ; extra == 'test'
Requires-Dist: pytest-cov ; extra == 'test'
Requires-Dist: pytest-mock ; extra == 'test'
